pytdxattest/__init__.py
pytdxattest/actor.py
pytdxattest/binaryblob.py
pytdxattest/ccel.py
pytdxattest/cli.py
pytdxattest/rtmr.py
pytdxattest/tdeventlog.py
pytdxattest/tdquote.py
pytdxattest/tdreport.py
pytdxattest/utility.py
pytdxattest-0.0.11.data/scripts/tdx_eventlogs
pytdxattest-0.0.11.data/scripts/tdx_extend_rtmr
pytdxattest-0.0.11.data/scripts/tdx_quote
pytdxattest-0.0.11.data/scripts/tdx_tdreport
pytdxattest-0.0.11.data/scripts/tdx_verify_rtmr
pytdxattest-0.0.11.dist-info/LICENSE
pytdxattest-0.0.11.dist-info/METADATA
pytdxattest-0.0.11.dist-info/WHEEL
pytdxattest-0.0.11.dist-info/top_level.txt
pytdxattest-0.0.11.dist-info/RECORD
