Metadata-Version: 2.1
Name: pytdxattest
Version: 0.0.11
Summary: UNKNOWN
Home-page: UNKNOWN
License: Apache License 2.0
Platform: UNKNOWN
Requires-Python: >=3.6.8
License-File: LICENSE
Requires-Dist: setuptools
Requires-Dist: wheel
